multicalibration/__init__.py
multicalibration/mcb.py
multicalibration/HJZ/adversary.py
multicalibration/HJZ/hjz.py
multicalibration/HJZ/online_learners.py
multicalibration/HJZ/utils.py
multicalibration/HKRR/hkrr.py
multicalibration-0.0.2.dist-info/LICENSE
multicalibration-0.0.2.dist-info/METADATA
multicalibration-0.0.2.dist-info/WHEEL
multicalibration-0.0.2.dist-info/top_level.txt
multicalibration-0.0.2.dist-info/RECORD
