Metadata-Version: 2.1
Name: multicalibration
Version: 0.0.2
Summary: Multicalibration post-processing in python.
Author-email: Siddartha Devic <sid.devic@gmail.com>, Dutch Hansen <none@gmail.com>
Project-URL: Homepage, https://github.com/sid-devic/multicalibration
Project-URL: Issues, https://github.com/sid-devic/multicalibration/issues
Classifier: Programming Language :: Python :: 3
Classifier: License :: OSI Approved :: MIT License
Classifier: Operating System :: OS Independent
Requires-Python: >=3.8
License-File: LICENSE
